feincms3_downloads/__init__.py
feincms3_downloads/checks.py
feincms3_downloads/plugins.py
feincms3_downloads/previews.py
feincms3_downloads/locale/de/LC_MESSAGES/django.mo
feincms3_downloads/locale/de/LC_MESSAGES/django.po
feincms3_downloads/templates/plugins/download.html
feincms3_downloads-0.5.3.dist-info/METADATA
feincms3_downloads-0.5.3.dist-info/WHEEL
feincms3_downloads-0.5.3.dist-info/licenses/LICENSE
feincms3_downloads-0.5.3.dist-info/RECORD
