Metadata-Version: 2.1
Name: feincms3-downloads
Version: 0.5.3
Summary: Downloads plugin for feincms3
Project-URL: Homepage, https://github.com/matthiask/feincms3-downloads/
Author-email: Matthias Kestenholz <mk@feinheit.ch>
License: MIT
License-File: LICENSE
Classifier: Development Status :: 4 - Beta
Classifier: Environment :: Web Environment
Classifier: Framework :: Django
Classifier: Intended Audience :: Developers
Classifier: License :: OSI Approved :: BSD License
Classifier: License :: OSI Approved :: MIT License
Classifier: Operating System :: OS Independent
Classifier: Programming Language :: Python
Classifier: Programming Language :: Python :: 3 :: Only
Classifier: Programming Language :: Python :: 3.8
Classifier: Programming Language :: Python :: 3.9
Classifier: Programming Language :: Python :: 3.10
Classifier: Programming Language :: Python :: 3.11
Classifier: Topic :: Internet :: WWW/HTTP :: Dynamic Content
Classifier: Topic :: Software Development
Classifier: Topic :: Software Development :: Libraries :: Application Frameworks
Requires-Python: >=3.8
Requires-Dist: django>=3.2
Requires-Dist: feincms3>=4
Requires-Dist: pillow
Provides-Extra: tests
Requires-Dist: coverage; extra == 'tests'
